[
    {
        "id": 0,
        "name": "Interregation av misstänkt individ nr 2331",
        "key_code": "QWERTY",
        "answer": "correct",
        "type": "video",
        "manuscript": "",
        "hints": null,
        "introduction": {
            "Initilizing": [ "Datalogg: Malmö Polisarkivet."],
            "fetching": [ "Hämtar relevant data från brottsregistret:", " <span class='highlighted-terminal terminal-connected'>100%</span>"],
            "brief": [ "Misstänkt för brott nr: 1337 - kodnamn - boogie_thief"],
            "brott": [ "Anledning till misstanke:", "Vittnen hävdar att individens favorithobby är att stjäla näsor från barn."],
            "starting": [ "Starta Interregation när redo . . ."]
        },
        "interrogation": {
            "first": {
                "video": "video1_id_1.mp4",
                "answers": [ "Ifrågasätt", "Spela förstående"]
            },
            "second": {
                "video": "video2_id_1.mp4",
                "answers": [ "Anklagande", "Försäkrande"]
            }
        }
    },
    {
        "id": 1,
        "name": "Kryptiska Färger",
        "key_code": "FKRX",
        "answer": "correct",
        "type": "pussle",
        "manuscript": "",
        "hints": null,
        "introduction": []
    },
    {
        "id": 2,
        "name": "Nyhetsmorgon i skåne",
        "key_code": "Bo och Bosses bänk",
        "answer": "correct",
        "type": "article",
        "manuscript": "",
        "hints": null,
        "introduction": []
    },
    {
        "id": 3,
        "name": "Mff-supportern intervju",
        "key_code": "SVEN-ÅKE NILSSON",
        "answer": "correct",
        "type": "video",
        "manuscript": "",
        "hints": null,
        "introduction": []
    },
    {
        "id": 4,
        "name": "__ ___ ._. . kod",
        "key_code": "GK8529",
        "answer": "correct",
        "type": "pussle",
        "manuscript": "",
        "hints": null,
        "introduction": []
    },
    {
        "id": 5,
        "name": "Förbjudna Föremål",
        "key_code": "Stora väskor",
        "answer": "correct",
        "type": "video",
        "manuscript": "",
        "hints": null,
        "introduction": []
    },
    {
        "id": 6,
        "name": "Bajspåsar & Skvallertanter",
        "key_code": "TALLRIKEN",
        "answer": "correct",
        "type": "video",
        "manuscript": "",
        "hints": null,
        "introduction": []
    },
    {
        "id": 7,
        "name": "Ketchup & korvar",
        "key_code": "TBA",
        "answer": "correct",
        "type": "sound",
        "manuscript": "",
        "hints": null,
        "introduction": []
    },
    {
        "id": 8,
        "name": "Margaretas Blomstergata",
        "key_code": "Special Tiger Eye",
        "answer": "correct",
        "type": "pussle",
        "manuscript": "",
        "hints": null,
        "introduction": []
    }
]